clumpick/__init__.py
clumpick/__main__.py
clumpick/default_palette.txt
clumpick/funcs.py
clumpick/html.py
clumpick/script.js
clumpick-0.1.0.dist-info/METADATA
clumpick-0.1.0.dist-info/WHEEL
clumpick-0.1.0.dist-info/RECORD
